security/__init__.py
security/_version.py
security/exceptions.py
security/safe_command/__init__.py
security/safe_command/api.py
security/safe_requests/__init__.py
security/safe_requests/api.py
security/safe_requests/host_validators.py
security-1.3.0.dist-info/LICENSE.txt
security-1.3.0.dist-info/METADATA
security-1.3.0.dist-info/WHEEL
security-1.3.0.dist-info/top_level.txt
security-1.3.0.dist-info/RECORD
