Metadata-Version: 2.1
Name: security
Version: 1.3.0
Summary: The security toolkit for the Python community
Author-email: Pixee <python@pixee.ai>
License: MIT License
Project-URL: Homepage, https://github.com/pixee/python-security
Project-URL: Repository, https://github.com/pixee/python-security
Keywords: security,appsec
Requires-Python: >=3.8
License-File: LICENSE.txt
Requires-Dist: requests
